{
  "app.title": "Launcher",
  "app.status": "status",
  "app.status.connected.online": "online",
  "app.status.connected.offline": "offline",
  "app.exit": "Exit",
  "app.tabs.applications": "Applications",
  "app.tabs.update": "Add & Update",
  "app.settings.title": "settings",
  "app.settings.visualisation": "visualisation",
  "app.settings.account.settings": "account settings",
  "app.settings.label.theme": "theme",
  "app.settings.label.language": "language",
  "app.settings.save.success": "The apps settings save successful",
  "app.settings.save.error": "The apps settings save error",
  "app.color.theme.light": "light",
  "app.color.theme.dark": "dark",
  "app.action.open": "open",
  "app.action.update": "update",
  "app.action.install": "install",
  "app.list.empty": "No applications found",
  "app.update.search.placeholder": "Search for applications name",
  "app.installed.load.info.error": "No installs info available",
  "app.update.load.info.error": "No update info available",
  "app.install.success": "The {name} application was installed success. You can open it from 'Applications' section",
  "app.install.error": "The {name} application installing error.",
  "app.download.error": "The {name} application downloading error."
}
